{
  "config_file": "/tmp/metric_output_analysis_off.json",
  "problem_name": "Metric Domain Example Complex",
  "solutions_found": 1,
  "solve_time_ms": 1,
  "rules_applied": 6,
  "solutions": [
    {
      "solution_index": 0,
      "voices": [
        {
          "voice": 0,
          "pitch_solution": [76, 77, 72, 65, 64, 71, 79, 69, 74, 67, 62, 60, 71, 79, 72, 64, 74, 71, 65, 62, 71, 71, 60, 69],
          "rhythm_solution": [2, 2, 2, 2, 2, 2, 2, 2, 2, 2, 2, 2, 2, 2, 2, 2, 2, 2, 2, 2, 2, 2, 2, 2],
          "pitch_names": ["E5", "F5", "C5", "F4", "E4", "B4", "G5", "A4", "D5", "G4", "D4", "C4", "B4", "G5", "C5", "E4", "D5", "B4", "F4", "D4", "B4", "B4", "C4", "A4"],
          "rhythm_names": ["1/4", "1/4", "1/4", "1/4", "1/4", "1/4", "1/4", "1/4", "1/4", "1/4", "1/4", "1/4", "1/4", "1/4", "1/4", "1/4", "1/4", "1/4", "1/4", "1/4", "1/4", "1/4", "1/4", "1/4"]
        },
        {
          "voice": 1,
          "pitch_solution": [59, 69, 72, 62, 64, 74, 71, 67, 55, 65, 60, 57, 64, 60, 72, 74, 69, 74, 62, 65, 55, 64, 55, 67],
          "rhythm_solution": [1, 1, 1, 1, 1, 1, 1, 1, 1, 1, 1, 1, 1, 1, 1, 1, 1, 1, 1, 1, 1, 1, 1, 1],
          "pitch_names": ["B3", "A4", "C5", "D4", "E4", "D5", "B4", "G4", "G3", "F4", "C4", "A3", "E4", "C4", "C5", "D5", "A4", "D5", "D4", "F4", "G3", "E4", "G3", "G4"],
          "rhythm_names": ["1/8", "1/8", "1/8", "1/8", "1/8", "1/8", "1/8", "1/8", "1/8", "1/8", "1/8", "1/8", "1/8", "1/8", "1/8", "1/8", "1/8", "1/8", "1/8", "1/8", "1/8", "1/8", "1/8", "1/8"]
        }
      ],
      "metric_signature_numerators": [4, 4, 4, 4, 4, 4, 4, 4, 3, 3, 3, 3, 3, 3, 2, 2, 2, 2, 4, 4, 4, 4, 4, 4],
      "metric_signature": ["4/4", "4/4", "4/4", "4/4", "4/4", "4/4", "4/4", "4/4", "3/4", "3/4", "3/4", "3/4", "3/4", "3/4", "2/4", "2/4", "2/4", "2/4", "4/4", "4/4", "4/4", "4/4", "4/4", "4/4"]
    }
  ]
}
