{
  "name": "Template - True/False Basic Rule",
  "description": "Edit domains and hard constraints. true_false rules are strict constraints.",
  "solution_length": 6,
  "num_voices": 1,
  "search_options": {
    "random_seed": 0,
    "timeout_ms": 5000,
    "branching": "first_fail"
  },
  "voices": [
    {
      "rhythm": {
        "duration_values": ["1/8", "1/4"]
      },
      "pitch": {
        "midi_values": [60, 62, 64, 65, 67, 69, 71, 72]
      }
    }
  ],
  "export_path": "output",
  "rules": [],
  "dynamic_rules": [
    {
      "id": "hard_no_repeat_0_1",
      "type": "basic_constraint",
      "expression": {
        "operator": "!=",
        "left": "voice[0].pitch[0]",
        "right": "voice[0].pitch[1]"
      },
      "mode": "true_false",
      "description": "Hard constraint template"
    }
  ]
}
