{
  "name": "Template - Heuristic Switch Sliding Window",
  "description": "Boolean preference rule over all adjacent note pairs.",
  "solution_length": 8,
  "num_voices": 1,
  "search_options": {
    "random_seed": 0,
    "timeout_ms": 5000,
    "branching": "first_fail"
  },
  "voices": [
    {
      "rhythm": {
        "duration_values": ["1/8", "1/4"]
      },
      "pitch": {
        "midi_values": [55, 57, 59, 60, 62, 64, 65, 67, 69, 71]
      }
    }
  ],
  "file_name": "output/template_heur_switch_sliding_window_1v",
  "rules": [],
  "dynamic_rules": [
    {
      "id": "prefer_stepwise",
      "type": "heuristic_preference",
      "wildcard_type": "sliding_window",
      "pattern_offsets": [0, 1],
      "step_size": 1,
      "expression": "abs(voice[v].pitch[i+1] - voice[v].pitch[i]) <= 2",
      "mode": "heur_switch",
      "weight": 2,
      "priority": 5,
      "direction": "maximize",
      "description": "Edit threshold/weight/priority"
    }
  ]
}
